{
    "threeDSStatus": [
        {
            "ds_status_response": "Authenticated",
            "ds_status_description": "3DS was is avaiable and successfully authenticated.",
            "ds_status_recommendation": "No action needed."
        },
        {
            "ds_status_response": "Unavailable",
            "ds_status_description": "3DS was unavailable for this transaction.",
            "ds_status_recommendation": "Please try again later or contact support."
        },
        {
            "ds_status_response": "Failed",
            "ds_status_description": "The 3DS authentication process failed.",
            "ds_status_recommendation": "Please verify your information and try again."
        },
        {
            "ds_status_response": "Error",
            "ds_status_description": "An error occurred during 3DS processing.",
            "ds_status_recommendation": "Please contact support for assistance."
        }
    ]
}